timelib_jack/__init__.py
timelib_jack/core.py
timelib_jack/examples.py
timelib_jack/utils.py
timelib_jack-1.0.0.dist-info/METADATA
timelib_jack-1.0.0.dist-info/WHEEL
timelib_jack-1.0.0.dist-info/top_level.txt
timelib_jack-1.0.0.dist-info/RECORD
