Metadata-Version: 2.4
Name: timelib-jack
Version: 1.0.0
Summary: مكتبة توقيت متقدمة، Async + Cron + Retry + Priority + Pause/Resume + Monitoring + Time protection
Author: Jack
Classifier: Programming Language :: Python :: 3.9
Classifier: License :: OSI Approved :: MIT License
Classifier: Operating System :: OS Independent
Classifier: Intended Audience :: Developers
Classifier: Topic :: Utilities
Requires-Python: >=3.9
Dynamic: author
Dynamic: classifier
Dynamic: requires-python
Dynamic: summary
